bscpylgtv/__init__.py
bscpylgtv/_version.py
bscpylgtv/buttons.py
bscpylgtv/cal_commands.py
bscpylgtv/constants.py
bscpylgtv/endpoints.py
bscpylgtv/exceptions.py
bscpylgtv/handshake.py
bscpylgtv/lut_tools.py
bscpylgtv/storage_proto.py
bscpylgtv/storage_sqlitedict.py
bscpylgtv/utils.py
bscpylgtv/webos_client.py
bscpylgtv-0.5.0.dist-info/LICENSE.txt
bscpylgtv-0.5.0.dist-info/METADATA
bscpylgtv-0.5.0.dist-info/WHEEL
bscpylgtv-0.5.0.dist-info/entry_points.txt
bscpylgtv-0.5.0.dist-info/top_level.txt
bscpylgtv-0.5.0.dist-info/zip-safe
bscpylgtv-0.5.0.dist-info/RECORD
