Metadata-Version: 2.1
Name: bscpylgtv
Version: 0.5.0
Summary: Library to control webOS based LG TV devices.
Home-page: https://github.com/chros73/bscpylgtv
Author: chros
Author-email: chros73@gmail.com
License: UNKNOWN
Keywords: webos,tv
Platform: UNKNOWN
Requires-Python: >=3.8
Requires-Dist: websockets (>=8.1)
Requires-Dist: sqlitedict
Provides-Extra: with_calibration
Requires-Dist: numpy (>=1.17.0) ; extra == 'with_calibration'
